nemsdk/__init__.py
nemsdk/fee.py
nemsdk/message.py
nemsdk/mosaic.py
nemsdk/network.py
nemsdk/request.py
nemsdk/serializer.py
nemsdk/tx.py
nemsdk/tx_type.py
nemsdk/tx_version.py
nemsdk/com/__init__.py
nemsdk/com/requests/__init__.py
nemsdk/com/requests/_client.py
nemsdk/com/requests/account.py
nemsdk/com/requests/chain.py
nemsdk/com/requests/namespace.py
nemsdk/com/requests/nis.py
nemsdk/com/requests/node.py
nemsdk/com/requests/transaction.py
nemsdk/com/websockets/__init__.py
nemsdk/crypto/__init__.py
nemsdk/crypto/key_pair.py
nemsdk/crypto/message.py
nemsdk/utils/__init__.py
nemsdk/utils/convert.py
nemsdk/utils/time.py
nemsdk-0.0.0.dist-info/METADATA
nemsdk-0.0.0.dist-info/RECORD
nemsdk-0.0.0.dist-info/WHEEL
nemsdk-0.0.0.dist-info/top_level.txt
test/__init__.py
test/helpers.py
test/test_fee.py
test/test_message.py
test/test_serializer.py
test/com/__init__.py
test/com/requests/__init__.py
test/com/requests/test_account.py
test/com/requests/test_chain.py
test/com/requests/test_namespace.py
test/com/requests/test_nis.py
test/com/requests/test_node.py
test/com/requests/test_transaction.py
test/crypt/__init__.py
test/crypt/test_message.py
test/tx/__init__.py
test/tx/test_multisig_mixin.py
test/tx/test_transfer_v1.py
test/tx/test_transfer_v2.py
