Metadata-Version: 2.1
Name: nemsdk
Version: 0.0.0
Summary: UNKNOWN
Home-page: UNKNOWN
Author: UNKNOWN
Author-email: UNKNOWN
License: MIT
Platform: UNKNOWN
Requires-Dist: requests
Requires-Dist: nem-ed25519
